AUTHORS
CHANGELOG.txt
DESCRIPTION
LICENSE
MANIFEST.in
README.rst
setup.py
django_multilingual_events.egg-info/PKG-INFO
django_multilingual_events.egg-info/SOURCES.txt
django_multilingual_events.egg-info/dependency_links.txt
django_multilingual_events.egg-info/requires.txt
django_multilingual_events.egg-info/top_level.txt
multilingual_events/__init__.py
multilingual_events/admin.py
multilingual_events/cms_apps.py
multilingual_events/cms_plugins.py
multilingual_events/forms.py
multilingual_events/models.py
multilingual_events/settings.py
multilingual_events/sitemaps.py
multilingual_events/urls.py
multilingual_events/views.py
multilingual_events/fixtures/bootstrap.json
multilingual_events/locale/de/LC_MESSAGES/django.mo
multilingual_events/locale/de/LC_MESSAGES/django.po
multilingual_events/migrations/0001_initial.py
multilingual_events/migrations/0002_eventagendaday_eventagendasession_eventagendatalk_eventpluginmodel.py
multilingual_events/migrations/0003_auto_20220506_0248.py
multilingual_events/migrations/__init__.py
multilingual_events/templates/multilingual_events/event_detail.html
multilingual_events/templates/multilingual_events/event_list.html
multilingual_events/templates/multilingual_events/event_plugin.html
multilingual_events/templates/multilingual_events/partials/event_item.html
multilingual_events/templates/multilingual_events/plugins/event_agenda_day.html
multilingual_events/templates/multilingual_events/plugins/event_agenda_session.html
multilingual_events/templates/multilingual_events/plugins/event_agenda_talk.html
multilingual_events/templatetags/__init__.py
multilingual_events/templatetags/multilingual_events_tags.py
multilingual_events/tests/__init__.py
multilingual_events/tests/forms_tests.py
multilingual_events/tests/models_tests.py
multilingual_events/tests/multilingual_events_tags_tests.py
multilingual_events/tests/settings.py
multilingual_events/tests/test_settings.py
multilingual_events/tests/views_tests.py
multilingual_events/tests/test_app/__init__.py
multilingual_events/tests/test_app/models.py
multilingual_events/tests/test_app/urls.py
multilingual_events/tests/test_app/templates/base.html
multilingual_events/tests/test_app/templates/standard.html