Metadata-Version: 2.1
Name: django-multilingual-events
Version: 2.0.0
Summary: A simple event app to create event pages for events such as conferences.
Home-page: https://github.com/bitlabstudio/django-multilingual-events
Author: Martin Brochhaus
Author-email: martin.brochhaus@bitlabstudio.com
License: The MIT License
Keywords: django,event,i18n,multilingual,agenda,planning
Platform: OS Independent
License-File: LICENSE
License-File: AUTHORS
